barsapi.py
barsapi-1.2.dist-info/METADATA
barsapi-1.2.dist-info/WHEEL
barsapi-1.2.dist-info/RECORD
